{
  "main": {
    "id": "ecebe3bdbb0a4ae8",
    "type": "split",
    "children": [
      {
        "id": "f44f5770300fa439",
        "type": "tabs",
        "children": [
          {
            "id": "a154516fe81e68fe",
            "type": "leaf",
            "state": {
              "type": "markdown",
              "state": {
                "file": "source/_posts/计量经济学笔记.md",
                "mode": "source",
                "source": false
              }
            }
          }
        ]
      }
    ],
    "direction": "vertical"
  },
  "left": {
    "id": "c30d0b1d8d79d513",
    "type": "split",
    "children": [
      {
        "id": "b7c03d1a032b1673",
        "type": "tabs",
        "children": [
          {
            "id": "0946853ebc80b5e2",
            "type": "leaf",
            "state": {
              "type": "file-explorer",
              "state": {
                "sortOrder": "alphabetical"
              }
            }
          },
          {
            "id": "fd0f2e0eebaeb584",
            "type": "leaf",
            "state": {
              "type": "starred",
              "state": {}
            }
          },
          {
            "id": "4f6c2f8320f508c5",
            "type": "leaf",
            "state": {
              "type": "search",
              "state": {
                "query": "",
                "matchingCase": false,
                "explainSearch": false,
                "collapseAll": false,
                "extraContext": false,
                "sortOrder": "alphabetical"
              }
            }
          }
        ]
      }
    ],
    "direction": "horizontal",
    "width": 300
  },
  "right": {
    "id": "47a7799fe6c7cf5e",
    "type": "split",
    "children": [
      {
        "id": "c7a4c19a55862cec",
        "type": "tabs",
        "children": [
          {
            "id": "57c4637aaf32b653",
            "type": "leaf",
            "state": {
              "type": "backlink",
              "state": {
                "file": "source/_posts/计量经济学笔记.md",
                "collapseAll": false,
                "extraContext": false,
                "sortOrder": "alphabetical",
                "showSearch": false,
                "searchQuery": "",
                "backlinkCollapsed": false,
                "unlinkedCollapsed": true
              }
            }
          },
          {
            "id": "5aa493fa47c459c8",
            "type": "leaf",
            "state": {
              "type": "outgoing-link",
              "state": {
                "file": "source/_posts/计量经济学笔记.md",
                "linksCollapsed": false,
                "unlinkedCollapsed": true
              }
            }
          },
          {
            "id": "d03a75d68a0bc3a5",
            "type": "leaf",
            "state": {
              "type": "tag",
              "state": {
                "sortOrder": "frequency",
                "useHierarchy": true
              }
            }
          },
          {
            "id": "117501cf22d9f6fb",
            "type": "leaf",
            "state": {
              "type": "outline",
              "state": {
                "file": "source/_posts/计量经济学笔记.md"
              }
            }
          }
        ],
        "currentTab": 3
      }
    ],
    "direction": "horizontal",
    "width": 300,
    "collapsed": true
  },
  "left-ribbon": {
    "hiddenItems": {
      "switcher:Open quick switcher": false,
      "graph:Open graph view": false,
      "command-palette:Open command palette": false,
      "table-editor-obsidian:Advanced Tables Toolbar": false,
      "templater-obsidian:Templater": false
    }
  },
  "active": "a154516fe81e68fe",
  "lastOpenFiles": [
    "db.json",
    "public/medias/banner/bg.jpg",
    "public/medias/featureimages/4.jpg",
    "public/medias/featureimages/9.jpg",
    "public/medias/featureimages/15.jpg",
    "public/medias/featureimages/16.jpg",
    "public/medias/featureimages/24.jpg",
    "public/medias/featureimages/1.jpg",
    "public/medias/featureimages/21.jpg",
    "public/medias/featureimages/19.jpg",
    "public/medias/featureimages/18.jpg",
    "public/pdf/MNISTClassificationWithMLP_于雨琛_2020011846.pdf",
    "public/libs/valine/av-min.js",
    "public/libs/materialize/materialize.min.js",
    "public/libs/gitment/gitment-default.css",
    "public/libs/aplayer/APlayer.min.js",
    "public/libs/gitalk/gitalk.min.js",
    "public/libs/codeBlock/clipboard.min.js",
    "public/libs/dplayer/DPlayer.min.js",
    "public/libs/tocbot/tocbot.css",
    "public/libs/aos/aos.css",
    "source/_posts/固定收益证券分析笔记（更新中）.md",
    "source/_posts/计量经济学笔记.md",
    "source/_posts/国际金融市场笔记（更新中）.md",
    "source/_posts/公司金融笔记.md",
    "source/_posts/博弈论与机制设计笔记（更新中）.md",
    "source/_posts/投资学笔记.md",
    "scaffolds/template.md",
    "source/_posts/MNIST Classification with MLP.md",
    "node_modules/hexo-pdf/README.md",
    "node_modules/hexo-pdf/node_modules/ejs/Readme.md",
    "node_modules/hexo-pdf/node_modules/ejs/History.md",
    "source/about/index.md",
    "source/_posts/托福口语.md",
    "source/_posts/衣戈猜想.md",
    "source/_posts/hello-hexo.md",
    "source/_posts/托福写作提纲.md",
    "source/gallery/index.md",
    "source/tags/index.md",
    "source/_posts/hello-world.md",
    "scaffolds/post.md",
    "scaffolds/draft.md",
    "scaffolds/page.md",
    "source/_posts/hello hexo.md",
    "source/_posts/ceshi.md",
    "thinking/电影/ceshi.md"
  ]
}